{
    "title": "Apple pie cookies",
    "category": "Ricette",
    "description": "Per preparare gli apple pie cookies per prima cose fate la pasta brisè: versate nel mixer dotato di lame la farinail burro a pezzi freddo di frigo, un pizzico di salee frullate il tutto per qualche secondo. Poi versate l'acqua ghiacciatae lavorate l'impasto ancora per 1-2 minuti fino a che si sarà compattato. Trasferitelo su una spianatoia, lavoratelo con le mani giusto per qualche istante dandogli la forma di un panetto.Avvolgete il panetto nella pellicola e lasciate riposare in frigorifero per 40 minuti. Mentre la brisè riposa occupatevi del ripieno. Sbucciatee tagliate le mele a piccoli dadini. Poi in una padella versate il burroe fatelo sciogliere a fuoco dolce, aggiungete le mele a dadini, la scorza di mezza arancia, insaporite con lo zucchero e la cannella in polvere(in alternativa potete usare la cannella in stecche per insaporire il composto) e infine versate il succo d’arancia filtrato. Cuocete a fuoco medio per 10 minuti, poi spegnete il fuoco e lasciate raffreddare. Riprendete il panetto di pasta e stendeteloa uno spessore di mezzo centimetroe ritagliate 24 dischi con un coppa pasta del diametro 6 cm. Spennellate i bordi con dell’acquae farcite il centro di metà dei dischetti con un cucchiaino di mele. Richiudete ciascun biscotto con un altro disco di pasta; pressate bene il bordo intorno per sigillarli. Adagiate i biscotti su una teglia da forno e incidete la superficie con un coltello, creando dei raggi. Mettete un pizzico di burro sopra ogni biscotto. Spolverizzate la superficie con lo zucchero di cannae cuocete in forno statico preriscaldato a 200° per 25 minuti. A cottura ultimata sfornate gli apple pie cookiese lasciateli intiepidire prima di gustarli.",
    "ingredients": [
        [
            "Farina 00",
            "200 g"
        ],
        [
            "Burro",
            "100 g"
        ],
        [
            "Acqua",
            "50 g"
        ],
        [
            "Sale fino",
            "1 pizzico"
        ],
        [
            "Mele Granny Smith",
            "300 g"
        ],
        [
            "Burro",
            "60 g"
        ],
        [
            "Zucchero",
            "60 g"
        ],
        [
            "Scorza d'arancia",
            "½"
        ],
        [
            "Succo d'arancia",
            "60 g"
        ],
        [
            "Cannella in polvere",
            "¼ cucchiaino"
        ],
        [
            "Zucchero di canna",
            "q.b."
        ],
        [
            "Burro",
            "q.b."
        ]
    ],
    "details": {
        "Difficoltà": "Facile",
        "Preparazione": "30 min",
        "Cottura": "35 min",
        "Dosi per": "12 pezzi"
    }
}