{"title": "Cassatelle di Carnevale", "category": "Dolci", "description": "Per preparare le cassatelle di Carnevale, in una ciotola ampia versate la farina, lo zucchero , un pizzico di sale le  uova a temperatura ambiente , il burro a pezzettini freddo ma non di frigo ,aromatizzate con la scorza di limone  e con quella d'arancia  e per finire insaporite l\u2019impasto con il marsala .\u00a0Impastate a mano gli ingredienti  e una volta che avrete raccolto i liquidi, trasferite l\u2019impasto su una spianatoia , lavoratelo finch\u00e9 non sar\u00e0 liscio e compatto .\u00a0Copritelo con pellicola  e lasciatelo riposare per  minuti fuori dal frigorifero. Nel frattempo occupatevi del ripieno: tritate finemente con un coltello il cioccolato fondente  avendo cura di non lasciare pezzi troppo grossi che potrebbero bucare la pasta in cottura. In una ciotola versate la ricotta di pecora, lo zucchero ,aromatizzate con la cannella  e versate il cioccolato tritato in precedenza . Mescolate con la forchetta per amalgamare gli ingredienti .Tenete da parte il ripieno  e riprendete l'impasto delle cassatelle: dividetela il panetto a met\u00e0  quindi stendetelo con la macchina tirapasta  fino al numero , ottenendo cos\u00ec uno spessore di circa  mm.\u00a0Una volta tirata la sfoglia, dividete a met\u00e0 il rettangolo e ricavate dei dischi con un coppapasta del diametro di , cm . Adagiate un cucchiaino di impasto al centro dei dischetti  bagnate i bordi con poca acqua , in modo che il ripieno, ripiegando la pasta, si sigilli perfettamente.Richiudete le cassatelle formando una mezzaluna e sigillando bene i bordi, pressando con il dorso della mano tutto intorno . Ritagliate il bordo del semicerchio, rifilando la parte con il ripieno, con un coppapasta dentellato cos\u00ec da creare un bordo decorato . Proseguite cos\u00ec per tutto il resto dell'impasto: con le dosi indicate otterrete circa  pezzi. Una volta pronte potete friggere le vostre cassatelle di Carnevale: mettete a scaldare l\u2019olio di semi in un tegame dai bordi alti e quando avr\u00e0 raggiunto al temperatura di \u00b0 (da misurare con un termometro da cucina), immergete le cassatelle delicatamente e poche alla volta  cos\u00ec da non abbassare troppo la temperatura dell\u2019olio.Cuocete le cassatelle per circa  minuti; una volta cotte , scolatele su carta assorbente . Una volta intiepidite spolverizzate le cassatelle di Carnevale con zucchero a velo a piacere e servitele subito !", "ingredients": [["Farina 00", "300 g"], ["Burro", "30 g"], ["Uova", "medie (a temperatura ambiente) 2"], ["Zucchero", "30 g"], ["Scorza d'arancia", "1"], ["Scorza di limone", "1"], ["Marsala", "20 g"], ["Sale fino", "1 pizzico"], ["Ricotta di pecora", "300 g"], ["Cioccolato fondente", "100 g"], ["Cannella in polvere", "\u00bd cucchiaino"], ["Zucchero", "100 g"], ["Olio di semi", "q.b."], ["Zucchero a velo", "q.b."]], "contesto": "Il risultato finale delle cassatelle di Carnevale sar\u00e0 un dolce fritto dal gusto armonioso e avvolgente, con un ripieno cremoso di ricotta di pecora e cioccolato fondente.\n\nOccasioni adatte:\nLe cassatelle di Carnevale sono perfette per celebrare il periodo di Carnevale, ma possono essere gustate anche in altre occasioni festive o come dessert speciale per una cena in famiglia.\n\nDieta adatta:\nQueste cassatelle sono adatte per una dieta bilanciata, ma non sono adatte a diete ipocaloriche o ipocaloriche.\n\nIntolleranze:\nLe cassatelle di Carnevale contengono uova, burro e cioccolato fondente, quindi non sono adatte per persone con intolleranze a questi alimenti. Se si \u00e8 intolleranti al lattosio, si pu\u00f2 sostituire la ricotta di pecora con un'altra alternativa senza lattosio. Se si \u00e8 celiaci, \u00e8 possibile utilizzare farina senza glutine per la preparazione dell'impasto."}