{
    "title": "Crespelle alle castagne ripiene di ricotta e funghi",
    "category": "Ricette",
    "description": "Per preparare le crespelle alle castagne ripiene di ricotta e funghi, come prima cosa sgusciate le uova in una ciotola, aggiungete un pizzico di sale e sbattete velocemente con una frusta. Unite la farina 00e metà della quantità del latte. Mescolate fino ad incorporare tutta la farina. Aggiungete quindi la farina di castagne. Versate il latte rimastoe mescolate fino a che non otterrete una pastella liscia e senza grumi. Lasciate riposare per 30 minuti in frigo coperta con pellicola. Scaldate una padella antiaderente e ungete leggermente con del burro. Versate in padella un mestolo di pastellae cuocete per 1-2 minuti, fino a che la pastella non sarà dorata, quindi giratela e cuocete l'altro lato. Ripetete lo stesso procedimento fino a esaurimento della pastella. Mettete le crespelle su un piattoe tenete da parte. Dedicatevi adesso alla preparazione del ripieno. Pulite i funghi e tagliateli a cubetti. In una padella versate un filo d'olio, aggiungete l'aglio e fate soffriggere per qualche minuto. Quando l'aglio sarà dorato, unite i funghie aggiustate di sale. Unite anche il prezzemolo tritatoe fate cuocere per 5-7 minuti, finché i funghi non saranno diventati teneri. In una ciotola mettete la ricotta, aggiungete i funghi, il parmigiano grattugiato, il pepe e se necessario aggiustate di sale. Mescolate fino ad ottenere un composto omogeneo. Mettete un cucchiaio di ripieno all'interno di una crespella quindi piegatela a metàe ancora a metà, ottenendo una forma triangolare. Ripetete lo stesso procedimento fino ad esaurimento delle crespelle. Ungete con olio una pirofila e disponete al suo interno le vostre crespelle. Cospargete la superficie con parmigiano grattugiatoe aggiungete dei piccoli cubetti di burro. Completate con prezzemolo tritatoe cuocete in forno statico a 220°C per 10-15 minuti, finché non cominciano a gratinare. Impiattate le vostre crespelle alle castagne ripiene di ricotta e funghie servite subito!",
    "ingredients": [
        [
            "Farina 00",
            "100 g"
        ],
        [
            "Farina di castagne",
            "100 g"
        ],
        [
            "Uova",
            "2"
        ],
        [
            "Latte",
            "400 ml"
        ],
        [
            "Sale",
            "1 pizzico"
        ],
        [
            "Burro",
            "per ungere la padella 10 g"
        ],
        [
            "Ricotta vaccina",
            "250 g"
        ],
        [
            "Funghi porcini",
            "200 g"
        ],
        [
            "Parmigiano Reggiano DOP",
            "grattugiato 50 g"
        ],
        [
            "Aglio",
            "1 spicchio"
        ],
        [
            "Olio extravergine d'oliva",
            "2 cucchiai"
        ],
        [
            "Sale",
            "q.b."
        ],
        [
            "Pepe nero",
            "q.b."
        ],
        [
            "Prezzemolo",
            "tritato q.b."
        ],
        [
            "Burro",
            "q.b."
        ],
        [
            "Parmigiano Reggiano DOP",
            "grattugiato q.b."
        ],
        [
            "Prezzemolo",
            "tritatato q.b."
        ]
    ],
    "details": {
        "Difficoltà": "Media",
        "Preparazione": "30 min",
        "Cottura": "25 min",
        "Dosi per": "4 persone",
        "Costo": "Basso"
    }
}