{"title": "Insalata di quinoa vegetariana", "category": "Piatti Unici", "description": "Per preparare l'insalata di quinoa vegetariana ponete su una teglia i peperoni, irrorateli con un filo di olio  e massaggiateli per cospargerli in modo uniforme. Cuocete in forno\u00a0statico preriscaldato a \u00b0 per  minuti, devono risultare ben abbrustoliti. Poi poneteli in un sacchetto per alimenti, ancora caldi, e lasciateli riposare per  minuti .Ora potete eliminare la pelle facilmente, insieme ai semi e al picciolo . Tagliateli\u00a0 a pezzetti  e poneteli in una ciotola. Tagliate grossolanamente le olive .Tagliate a cubetti la feta . Tritate l'erba cipollina  e il prezzemolo .Tostate in padella i pinoli . Nella ciotola con i peperoni unite anche la feta, le olive le erbe tritate e aggiungete basilico e menta spezzettati a mano .Aromatizzate con la scorza di mezzo limone . Tenete da parte il condimento e preparate la citronette: in un bicchiere alto versate il succo di un limone  e la senape .Aggiungete anche l'olio  e mezzo spicchio d'aglio tritato . Frullate tutto con il mixer a immersione per ottenere un'emulsione .Ora condite la quinoa con gli ingredienti raccolti in ciotola , i pinoli tostati  e la citronette . Mescolate per insaporire.Aggiustate di sale e pepe . Servite con feta a piacere sbriciolata . L'insalata di quinoa vegetariana \u00e8 pronta per essere gustata .", "ingredients": [["Quinoa", "(gi\u00e0 cotta, seguendo indicazioni sulla confezione) 400 g"], ["Peperoni rossi", "1"], ["Peperoni gialli", "1"], ["Olio extravergine d'oliva", "q.b."], ["Sale fino", "q.b."], ["Pepe nero", "q.b."], ["Olive taggiasche", "3 cucchiai"], ["Feta", "200 g"], ["Erba cipollina", "q.b."], ["Prezzemolo", "q.b."], ["Basilico", "10 foglie"], ["Menta", "4 foglie"], ["Pinoli", "4 cucchiai"], ["Limoni", "1"], ["Senape", "1 cucchiaino"], ["Aglio", "1 spicchio"], ["Feta", "da sbriciolare q.b."]], "contesto": "Il risultato finale sar\u00e0 un'insalata colorata e gustosa, con la quinoa come base ricca di proteine e fibre, arricchita da peperoni, olive, feta e erbe aromatiche. Il condimento a base di limone, senape e aglio conferir\u00e0 un sapore fresco e leggermente piccante. I pinoli daranno una nota croccante al piatto.\n\nQuesto piatto \u00e8 adatto per una cena leggera o come pranzo da portare in ufficio. \u00c8 ideale per chi segue un'alimentazione vegetariana, ma pu\u00f2 essere consumato anche da chi segue una dieta equilibrata e desidera aggiungere pi\u00f9 verdure e fibre alla propria alimentazione.\n\nLe persone con intolleranze alimentari dovrebbero fare attenzione alla feta, che contiene lattosio e pu\u00f2 essere problematica per chi \u00e8 intollerante al lattosio. Inoltre, chi \u00e8 intollerante al glutine dovrebbe verificare che la quinoa utilizzata sia certificata senza glutine."}