{"title": "Irish coffee semiliquido", "category": "Dolci", "description": "Per preparare l\u2019Irish coffee semiliquido fate scaldare in un pentolino la panna con il latte e lo zucchero , cuocendo il tutto a fuoco basso e mescolando spesso, fino al raggiungimento del bollore. Spegnete il fuoco e nel frattempo mettete in ammollo la gelatina in abbondante acqua fredda per  minuti . Fate scaldare il whiskey in un pentolino, a fuoco basso per  minuti ,quindi scolate la gelatina, che avr\u00e0 assunto una consistenza gelatinosa, strizzatela bene con le mani ed unitela al whiskey ; mescolando spesso per farla sciogliere completamente. Unite il tutto al composto con la panna . Prendete quattro bicchieri medi di vetro e versate in ciascuno di essi  gr della crema al whiskey ottenuta; riponeteli in frigorifero, coperti da pellicola, per  ore .Intanto preparate il caff\u00e8 con la caffettiera: per ottenere un ottimo caff\u00e8, riempite la caldaia della vostra caffettiera con l\u2019acqua fredda e possibilmente povera di calcare, facendo ben attenzione a non superare la valvola di sicurezza  (altrimenti otterrete un caff\u00e8 pi\u00f9 lungo). Riempite il filtro con il caff\u00e8 macinato, formando una montagnetta che livellerete battendo il filtro sul tavolo con movimenti decisi (-). Non pressate con il cucchiaino, n\u00e8 operate fori sulla superficie.Chiudete la caffettiera molto stretta , cos\u00ec che il caff\u00e8 non fuoriesca dai lati mentre sale, e ponetala su una fiamma bassa e costante per ottenere un caff\u00e8 corposo. Man mano che il caff\u00e8 sale si former\u00e0 una schiumetta densa : vi consigliamo di non lasciar gorgogliare troppo a lungo il caff\u00e8 per mantenere intatta la sua dolcezza e il suo aroma. Il vostro caff\u00e8 \u00e8 pronto: prima di utilizzarlo mescolatelo direttamente nella moka con un cucchiaino per rendere il caff\u00e8 pi\u00f9 omogeneo. Estraete i bicchieri con la crema al whiskey dal frigorifero e versate  ml (poco pi\u00f9 di mezza tazzina) di caff\u00e8 caldo sulla superficie di ciascuno , avendo cura di compiere questa operazione lentamente, con l'aiuto del dorso di un cucchiaino, per non mescolare il caff\u00e8 alla crema.", "ingredients": [["Latte intero", "124 ml"], ["Panna fresca liquida", "150 g"], ["Zucchero", "50 g"], ["Gelatina in fogli", "4 g"], ["Whisky", "50 ml"], ["Caff\u00e8", "160 ml"]], "contesto": "Il risultato finale di questa ricetta sar\u00e0 un delizioso Irish coffee semiliquido, con una consistenza cremosa e un sapore equilibrato tra il caff\u00e8, il whisky e la dolcezza della panna.\n\nQuesto dessert \u00e8 adatto per occasioni speciali come feste di compleanno, cene eleganti o semplicemente come fine pasto per un tocco raffinato.\n\nQuesta ricetta non \u00e8 adatta per diete ipocaloriche o a basso contenuto di grassi, in quanto contiene latte intero, panna fresca e zucchero. \u00c8 consigliabile consumarlo con moderazione e come parte di una dieta equilibrata.\n\nLe persone con intolleranze al lattosio o alla gelatina potrebbero non essere in grado di consumare questo dessert. Si consiglia di sostituire il latte intero con latte senza lattosio e utilizzare gelatina vegetale per adattarlo alle esigenze dietetiche specifiche."}