{"title": "Melanzane alla sarda", "category": "Contorni", "description": "Per preparare le melanzane alla sarda, potete utilizzare sia la variet\u00e0 violetta allungata che quella tonda. Per prima cosa lavate le melanzane e tagliatele a fette di mezzo centimetro  . Con la lama di un coltello incidete ogni fetta di melanzana praticando delle righe verticali, orizzontali e trasversali, in modo da formare un disegno a scacchiera. Questa operazione servir\u00e0 a far perdere pi\u00f9 facilmente l'umore amarogno delle melanzane e a facilitare la cottura uniforme . Salate le fette di melanzana e adagiatele in uno scolapasta . Copritele con un piatto sul quale metterete un peso in modo da comprimerle e lasciatele cos\u00ec per una mezz\u2019ora, in modo che perdano il liquido amarognolo.Nel frattempo lavate i pomodori, tagliateli a met\u00e0 e scavate l\u2019interno delicatamente con un coltellino per eliminare i semi ( - ). Ora tagliateli a pezzetti di mezzo centimetro  e versateli in una ciotola.A questo punto condite i pomodori: aggiungerete gli spicchi di aglio  e i tre cucchiai di prezzemolo tritati finemente, il sale  e infine l\u2019olio . Mescolate e lasciate macerare per qualche minuto i pezzetti di pomodori con il condimento.Intanto, trascorsa la mezz\u2019ora, riprendete le fette di melanzane e controllate che abbiano rilasciato l\u2019acqua amarognola . Sciacquatele sotto l\u2019acqua corrente fredda  e poi asciugatele per bene con carta da cucina o con un panno. Poi, scaldate il forno statico a \u00b0-\u00b0. Ungete una pirofila di  cm dai bordi alti con olio d'oliva e iniziate a formare uno strato di melanzane .Coprite poi con uno strato di pomodorini tagliati . Continuate in questo modo fino a quando avrete esaurito tutte le melanzane, come illustrato nella foto . Poi infornate la pirofila, in forno statico gi\u00e0 caldo e cuocete a \u00b0 per almeno  minuti. Sfornate e servite le melanzane calde o fredde a seconda dei vostri gusti .", "ingredients": [["Aglio", "2 spicchi"], ["Olio extravergine d'oliva", "q.b."], ["Sale fino", "q.b."], ["Pepe nero", "q.b."], ["Melanzane", "970 g"], ["Pomodori ramati", "500 g"], ["Prezzemolo", "tritato 3 cucchiai"]], "contesto": "Il risultato finale di questa ricetta sono delle melanzane alla sarda, un contorno gustoso e ricco di sapori mediterranei. Le melanzane vengono tagliate a fette, saltate in padella e successivamente cotte in forno con pomodori ramati, aglio, olio extravergine d'oliva, prezzemolo tritato, sale e pepe nero. Il risultato sar\u00e0 delle melanzane morbide e saporite, arricchite dal sapore fresco e aromatico del prezzemolo.\n\nQuesto piatto \u00e8 adatto per un pranzo o una cena in famiglia, da servire come contorno a piatti di carne o pesce. \u00c8 ideale per chi ama la cucina mediterranea e desidera portare in tavola un piatto genuino e ricco di gusto.\n\nLe melanzane alla sarda sono adatte a chi segue una dieta vegetariana, in quanto non contengono carne o prodotti di origine animale, e possono essere adattate anche a una dieta vegana eliminando eventuali ingredienti di derivazione animale (come ad esempio il sale fino).\n\nLe persone con intolleranze o allergie devono fare attenzione agli ingredienti utilizzati. Questa ricetta contiene aglio, dunque non \u00e8 adatta a chi soffre di allergia all'aglio. Inoltre, \u00e8 importante verificare che gli altri ingredienti siano sicuri per chi ha intolleranze specifiche, come ad esempio l'intolleranza al glutine (verificare che il prezzemolo tritato non contenga glutine) o l'intolleranza ai pomodori. In caso di dubbi, \u00e8 sempre consigliabile consultare un medico o un nutrizionista."}