{"title": "Paccheri melanzane e ricotta", "category": "Primi piatti", "description": "Per preparare i paccheri melanzane e ricotta iniziate mettendo a bollire l'acqua che servir\u00e0 per la pasta, da salare a bollore. Mondate e tritate la cipolla , quindi versate l'olio in una padella ampia e fate scaldare . Unite la cipolla  e fatela rosolare, mescolando di tanto in tanto per farla dorare e appassire dolcemente. Versate la passata di pomodoro , aggiungete un mestolo d'acqua calda  e aggiustate di sale .Insaporite con pepe a piacere  e lasciate cuocere per  minuti con coperchio . Nel frattempo lavate, mondate e poi riducete le melanzane a cubetti di circa mezzo cm .Scaldate un giro d'olio in padella, unite le melanzane  e fatele rosolare fino a f\u00ecdorarle . Mettete una pentola di acqua salata sul fuoco e cuocete i paccheri  lasciandoli indietro di due minuti.\u00a0Scolate i paccheri direttamente nel sugo al pomodoro , aggiungete le melanzane , mescolate e portate a termine la cottura aggiungendo acqua di cottura della pasta  poco per volta se necessario.\u00a0Quando i paccheri saranno cotti, spegnete il fuoco e aggiungete la ricotta , mescolate per amalgamarla  e profumate con foglioline di basiilico. I paccheri melanzane e ricotta sono pronti per essere serviti\u00a0.", "ingredients": [["Paccheri", "320 g"], ["Melanzane", "250 g"], ["Ricotta vaccina", "150 g"], ["Passata di pomodoro", "200 g"], ["Cipolle", "\u00bd"], ["Olio extravergine d'oliva", "q.b."], ["Sale fino", "q.b."], ["Pepe nero", "q.b."], ["Basilico", "q.b."]], "contesto": "Il risultato finale di questa ricetta sar\u00e0 un piatto di paccheri conditi con una salsa cremosa di melanzane, ricotta e passata di pomodoro, arricchito con basilico fresco.\n\nOccasioni: Questo piatto \u00e8 adatto per pranzi o cene speciali in famiglia o con gli amici, in quanto \u00e8 gustoso e ricco di sapori.\n\nDieta: Questa ricetta \u00e8 adatta per una dieta onnivora.\n\nIntolleranze: Le persone intolleranti al lattosio possono sostituire la ricotta vaccina con una versione senza lattosio o con un'altra alternativa a base vegetale. Le persone intolleranti al glutine possono utilizzare paccheri senza glutine."}