{
    "title": "Pancake alla ricotta",
    "category": "Ricette",
    "description": "Per preparare i pancake alla ricotta, sciogliete il burro a fuoco dolcissimo (nella stessa padella antiaderente in cui poi cuocerete i pancake), lasciate intiepidire nel tempo di preparazione dell'impasto. In una ciotola rompete le uova intere, unite lo zuccheroe sbattete per un paio di minuti con una frusta a mano, fino a quando il composto risulterà leggermente spumoso; non dovrete montarlo. Aggiungete la ricottae mescolate sempre poco per amalgamarla. Quindi versate il lattee mescolate ancora brevemente. Setacciate a parte la farina e il lievito, unite un pizzico di sale. Quindi versate le polveri poco alla volta nel composto di uova, mescolando giusto il tempo necessario per far assorbire. Incorporate delicatamente il burro oramai intiepidito, lavorando l’impasto il meno possibile: otterrete una consistenza piuttosto densa, simile all’impasto di una torta. Non preoccupatevi se ci sono dei grumi, è normale. Passate la padella con un pezzo di carta da cucina così da eliminare il burro fuso in eccesso. Mettete a scaldare a fuoco medio e quando sarà calda ponete al centro un paio di cucchiai di composto, allargandolo leggermente la versata con il dorso del cucchiaio. Lasciate cuocere 3-4 minuti da un lato, controllate la doratura della base prima di girare il pancake: fate cuocere ancora 1-2 minuti dall'altro lato. Mettete il pancake pronto sul piatto da portata e continuate così fino a terminare l’impasto. Otterrete 7-8 pancake con queste dosi. Man mano che saranno pronti, adagiateli senza sovrapporli: evitando di schiacciarli non perderanno la loro sofficità. Solo al momento di servire, impilateli delicatamente come vuole la tradizione. Accompagnateli con yogurt, panna o una salsa ai frutti rossi, con frutta fresca o il classico e delizioso sciroppo d’acero!",
    "ingredients": [
        [
            "Uova",
            "(medie, a temperatura ambiente) 2"
        ],
        [
            "Ricotta vaccina",
            "100 g"
        ],
        [
            "Zucchero",
            "20 g"
        ],
        [
            "Latte intero",
            "(a temperatura ambiente) 70 g"
        ],
        [
            "Lievito in polvere per dolci",
            "6 g"
        ],
        [
            "Farina 00",
            "100 g"
        ],
        [
            "Sale fino",
            "1 pizzico"
        ],
        [
            "Burro",
            "25 g"
        ],
        [
            "Burro",
            "q.b."
        ]
    ],
    "details": {
        "Difficoltà": "Molto facile",
        "Preparazione": "15 min",
        "Cottura": "15 min",
        "Dosi per": "8 pezzi",
        "Costo": "Basso"
    }
}