{"title": "Pappa al pomodoro con primavera di verdurine", "category": "Primi piatti", "description": "Per preparare la pappa al pomodoro con primavera di verdurine iniziate tagliando a fette sottili il pane toscano . Adagiate le fette su una leccarda ricoperta con carta da forno senza sovrapporle . Infornate a \u00b0 C per / minuti. Una volta estratte dal forno, lasciatele intiepidire. Una volta che le fette di pane saranno intiepidite strofinateci sopra gli spicchi di aglio preventivamente sbucciati .Prendete ora una padella antiaderente dai bordi alti e adagiate all'interno il pane tostato. Versate sopra la passata di pomodori  e l'acqua  cos\u00ec che le fettine di pane vengano totalmente ricoperte dal liquido. Mescolate e fate cuocere a fuoco basso per - minuti, per far evaporare il liquido. Mescolate spesso per ottenere una cottura uniforme e ridurre il pane in pappa, salate e pepate.Intanto occupatevi delle verdure: mondate la cipolla rossa e tritatela , lavate e spuntate i fagiolini e riduceteli a piccoli dadini di mezzo cm circa , procedete allo stesso modo con le zucchine e melanzane . Pelate le carote e tagliatela anch'esse a dadini . Scaldate l'olio di oliva in un tegame quindi versate ilo trito di cipolle , rosolate per circa  minuti, quindi procedete inserendo mano a mano tutte le verdure in base ai tempi di cottura che richiedono.Versate per prime le melanzane , stufate per  minuti, quindi aggiungete le carote  e dopo altri  minuti i fagiolini e per ultime le zucchine . Proseguite la cottura a fiamma media per altri  minuti. Una volta pronte, insaporitele con il peperoncino in polvere  e profumate con le foglioline di basilico fresco .Nel frattempo la pappa al pomodoro sar\u00e0 giunta a cottura, spegnete il fuoco, aggiustate di sale e pepe  e guarnite con foglie di basilico . Servite la pappa al pomodoro con le verdurine precedentemente cotte .", "ingredients": [["Passata di pomodoro", "ciliegino 660 g"], ["Pane toscano", "raffermo 220 g"], ["Acqua", "750 g"], ["Aglio", "2 spicchi"], ["Sale fino", "q.b."], ["Pepe nero", "q.b."], ["Olio extravergine d'oliva", "q.b."], ["Basilico", "q.b."], ["Fagiolini", "100 g"], ["Zucchine", "150 g"], ["Carote", "130 g"], ["Cipolle rosse", "130 g"], ["Melanzane", "200 g"], ["Olio extravergine d'oliva", "20 g"], ["Basilico", "q.b."], ["Peperoncino in polvere", "\u00bd cucchiaino"], ["Sale fino", "q.b."]], "contesto": "Il risultato finale della pappa al pomodoro con primavera di verdurine sar\u00e0 un piatto rustico e saporito, con una consistenza morbida dovuta alla passata di pomodoro e al pane raffermo. Le verdurine primaverili aggiungono freschezza e colore al piatto, arricchendolo di sapore e nutrienti.\n\nQuesto piatto \u00e8 adatto per occasioni informali come pranzi o cene con amici e familiari. Pu\u00f2 essere servito sia caldo che freddo, quindi \u00e8 ottimo anche per picnic all'aperto o per un pranzo al sacco. La pappa al pomodoro con primavera di verdurine \u00e8 un piatto versatile e raffinato che si adatta a diverse situazioni.\n\nQuesta ricetta \u00e8 adatta a una dieta vegetariana, in quanto non contiene carne n\u00e9 pesce. Inoltre, il piatto pu\u00f2 essere reso vegan sostituendo il pane toscano con una versione senza ingredienti di origine animale. La pappa al pomodoro \u00e8 un piatto povero di grassi e calorie, ma ricco di fibre e sostanze benefiche per l'organismo.\n\nLe persone con intolleranze alimentari possono mangiare questa ricetta con alcune modifiche. Ad esempio, chi soffre di intolleranza al glutine pu\u00f2 utilizzare pane senza glutine al posto del pane toscano. Per chi \u00e8 intollerante al lattosio, \u00e8 consigliabile verificare che la passata di pomodoro ciliegino non contenga lattosio aggiunto. In caso di intolleranze specifiche, \u00e8 sempre consigliabile consultare un medico o un nutrizionista prima di consumare un piatto."}