{"title": "Pesce San Pietro in padella", "category": null, "description": "Per preparare il pesce San Pietro in padella come prima cosa posizionate i filetti su un tagliere, senza privarli della pelle e salateli . Lavate bene i pomodorini e tagliateli a met\u00e0, o in quarti se dovessero essere troppo grandi . Prendete le olive e denocciolatele .Passate al prezzemolo: tritatelo finemente . Ora schiacciate l'aglio, senza sbucciarlo, utilizzando la lama di un coltello, per il lato piatto . In una padella capiente versate un filo d'olio, aggiungete uno spicchio d'aglio  e lasciatelo rosolare.Trasferite all'interno della padella anche i filetti di pesce, posizionandoli con il lato della pelle rivolto verso il basso . Cuocete a fiamma media per  minuti, quindi sfumate con il vino bianco . Senza girare i filetti versate ripetutamente il sughetto sui filetti, per facilitarne la cottura .Aggiungete ora i pomodorini , le olive nere  e un pizzico di peperoncino .Proseguite la cottura per circa  minuti. Non dovrete girare i filetti, ma solo versare continuamente il sughetto sopra . Non appena i filetti diventeranno bianchi, significa che sono cotti. Aggiungete il prezzemolo tritato , regolate di sale se necessario e serviteli .", "ingredients": [["Pesce San Pietro", "filetti (con la pelle) 800 g"], ["Pomodorini ciliegino", "200 g"], ["Olive nere infornate", "50 g"], ["Vino bianco", "200 ml"], ["Aglio", "1 spicchio"], ["Peperoncino in polvere", "q.b."], ["Olio extravergine d'oliva", "q.b."], ["Sale fino", "q.b."], ["Prezzemolo", "2 ciuffi"]], "contesto": "Il risultato finale sar\u00e0 un piatto di Pesce San Pietro in padella dal sapore delicato e profumato, arricchito dalla dolcezza dei pomodorini ciliegino e il contrasto delle olive nere. La cottura in padella permetter\u00e0 al pesce di rimanere morbido e succulento, mentre il vino bianco dar\u00e0 un tocco di acidit\u00e0 e freschezza al piatto. Il prezzemolo fresco e il peperoncino in polvere aggiungeranno ulteriore profondit\u00e0 di sapore.\n\nQuesto piatto \u00e8 adatto per occasioni speciali o cene eleganti, grazie alla presentazione raffinata e al gusto ricercato. \u00c8 perfetto per chi segue una dieta mediterranea, ricca di pesce e verdure, ma \u00e8 anche adatto per chi \u00e8 alla ricerca di un pasto leggero e salutare. Le persone con intolleranze al glutine possono consumare questa ricetta, purch\u00e9 verifichino che gli ingredienti utilizzati siano privi di glutine."}