{
    "title": "Piselli stufati con pancetta",
    "category": "Ricette",
    "description": "Per preparare i piselli stufati con pancetta per prima cosa sbaccellate i piselliraccogliendoli in una ciotola, dovreste ottenerne circa 450 g. Passate alla pancetta: tagliatela prima a fette. Da queste ottenete delle striscioline. Tritate lo scalognoe spostatevi ai fornelli. Scaldate un filo d'olio in un tegame e unite lo scalogno. Cuocete due minuti a fuoco medio-basso con un pizzico di sale (facoltativo), unite poi la pancetta e fate cuocere 3-4 minuti. Aggiungete i pisellie un pizzico di sale. Bagnate con l’acquae coprite con il coperchio facendo cuocere circa 12-13 minuti, mescolando di tanto in tanto. Aggiustate di sale a piacere facendo attenzione alla pancetta che è sapida. Terminata la cottura spegnete e servite i vostri piselli con pancetta!",
    "ingredients": [
        [
            "Pisellini",
            "(450 g da puliti) 2 kg"
        ],
        [
            "Pancetta affumicata",
            "100 g"
        ],
        [
            "Acqua",
            "150 g"
        ],
        [
            "Olio extravergine d'oliva",
            "q.b."
        ],
        [
            "Scalogno",
            "1"
        ],
        [
            "Sale fino",
            "q.b."
        ]
    ],
    "details": {
        "Difficoltà": "Molto facile",
        "Preparazione": "15 min",
        "Cottura": "20 min",
        "Dosi per": "4 persone",
        "Costo": "Basso"
    }
}