{"title": "Spaghetti al Chianti", "category": "Primi piatti", "description": "Per preparare gli spaghetti al Chianti mondate, lavate e affettate finemente il porro , eliminando le foglie esterne pi\u00f9 dure. Tenete da parte qualche rondella di porro per la guarnizione finale e mettete il restante ad appassire, a fuoco dolce, in una padella antiaderente con  gr di burro (-).Quando il porro sar\u00e0 ben appassito aggiungete il vino Chianti , una grattugiata di noce moscata  ed un pizzico di sale. Fate restringere il tutto per qualche minuto a fuoco moderato, finch\u00e9 l\u2019alcool del vino sar\u00e0 completamente evaporato. A questo punto trasferite il composto in un mixer  e frullate il tutto fino ad ottenere una consistenza cremosa; salate e pepate a vostro piacimento.Tagliate a listarelle lo speck  e fatelo saltare in padella con il burro restante per un paio di minuti , finch\u00e9 non diventer\u00e0 croccante. Portate ad ebollizione abbondante acqua salata, quindi sbollentate per pochi secondi il porro che avevate tenuto da parte per la guarnizione , estraetelo e mettetelo da parte.Nella stessa acqua fate cuocere gli spaghetti  e scolateli al dente, conservando a parte un mestolo di acqua di cottura, quindi aggiungeteli allo speck  e fateli saltare insieme per un paio di minuti. Nella crema al vino aggiungete il mestolo di acqua di cottura ,mescolate e aggiungete il sugo cos\u00ec ottenuto alla pasta . Amalgamate molto bene tutti gli ingredienti, cospargete con il formaggio grattugiato  e decorate con le rondelle di porro . Gli spaghetti al Chianti sono pronti, serviteli e gustateli al momento!", "ingredients": [["Spaghetti", "400 g"], ["Burro", "45 g"], ["Noce moscata", "1 pizzico"], ["Pepe nero", "q.b."], ["Sale", "q.b."], ["Speck", "200 g"], ["Porri", "180 g"], ["Vino rosso", "Chianti 250 ml"], ["Parmigiano Reggiano DOP", "da grattugiare 20 g"]], "contesto": "Il risultato finale di questa ricetta \u00e8 un primo piatto di spaghetti conditi con una salsa al Chianti e arricchiti con speck croccante e porri.\n\n- Aspetto: Gli spaghetti al Chianti avranno un colore rosso intenso dovuto al vino e alla presenza del parmigiano Reggiano grattugiato sulla superficie.\n- Consistenza: Gli spaghetti saranno al dente e la salsa cremosa grazie al burro e al formaggio grattugiato.\n- Gusto: Il sapore sar\u00e0 caratterizzato dalla complessit\u00e0 del vino Chianti, dalle note speziate della noce moscata e del pepe nero, e dall'intensit\u00e0 del parmigiano Reggiano.\n\nQuesta ricetta \u00e8 adatta per una cena elegante o una serata speciale, perfetta da servire durante una cena in famiglia o con gli amici.\n\nQuesta ricetta non \u00e8 adatta per persone che seguono una dieta vegana o senza glutine. Tuttavia, pu\u00f2 essere adatta a una dieta bilanciata se consumata in quantit\u00e0 moderate.\n\nLe persone con intolleranze al lattosio non dovrebbero consumare questa ricetta a meno che non utilizzi formaggio senza lattosio o sostituti del formaggio. Le persone con intolleranze al glutine possono optare per spaghetti senza glutine. Chi soffre di intolleranze al vino dovrebbe evitare di consumare questa ricetta."}