{"title": "Tagliatelle con calamari e pomodorini", "category": "Primi piatti", "description": "Per preparare le tagliatelle con calamari e pomodorini, iniziate dalla pasta fresca. Versate la farina in una ciotola (restate un p\u00f2 indietro con la dose in modo da aggiungerne in caso al bisogno). Create una conca e aggiungete al centro le uova a temperatura ambiente . Lavorate con un forchetta  e non appena le uova avranno assorbito un p\u00f2 di farina, proseguite impastando a mano fino ad ottenere un impasto omogeneo .\u00a0Continuate a lavorare l'impasto su un ripiano leggermente infarinato per almeno - minuti fino ad ottenere una consistenza liscia ed elastica. Maneggiate con energia ma evitando di strappare la maglia glutinica. Poi formate una palla  e avvolgetela nella pellicola trasparente . Lasciate riposare l'impasto a temperatura ambiente per almeno  minuti. Dopo il riposo dividete il panetto in tre parti  per stenderlo pi\u00f9 facilmente.\u00a0Infarinate accuratamente una parte e appiatitela, conservate nella pellicola le altre due porzioni cos\u00ec non si seccheranno. Prendete la macchina tirapasta e posizionatela sullo spessore n\u00b0 , ovvero al massimo spessore e fate passare il panetto tra i rulli per ottenere una prima sfoglia piuttosto spessa, poi ripiegate i due lembi della sfoglia verso il centro per conferire una forma pi\u00f9 regolare quindi infarinatela leggermente e ripassatela tra i rulli, proseguite in questo modo pi\u00f9 volte fino ad arrivare allo spessore n\u00b0 . Adagiate la sfoglia ottenuta sulla spianatoia infarinata pareggiate con un tarocco (o un coltello) le estremit\u00e0 per rendere regolare la pasta, quindi dividetela in due parti  cos\u00ec da maneggiarla pi\u00f9 facilmente. Ripassatela nella macchina tirapasta allo spessore  perch\u00e8 nel frattempo si sar\u00e0 un p\u00f2 ritirata nel lavorarla. Cospargetela con un p\u00f2 di semola su entrambi i lati  e lasciate seccare le sfoglie  minuti per lato.\u00a0Ora prendete una sfoglia, ripiegate un lembo fino a due terzi circa  poi iniziate ad arrotolare creando un rotolino molto piatto, tenendo la chiusura verso l'alto . Tagliate il rotolo di pasta a fettine di  mm di spessore .\u00a0Prendete le tagliatelle dalle estremit\u00e0, stendete le tagliatelle sulla mano , quindi arrotolate attorno alle dita per creare un nido  e adagiatelo sula spianatoia leggermente infarinata . Proseguite fino a terminare tutto l'impasto .\u00a0Assicuratevi che i calamari siano ben puliti, tagliate il mantello a striscioline  e i tentacoli a pezzetti . Lavate i pomodorini e tagliateli in quarti . Mettete sul fuoco una pentola colma d'acqua, leggermente salata, che servir\u00e0 per la cottura della pasta.Ora prendete una padella, versate un filo di olio e aggiungete l\u2019aglio. Scaldate per un paio di minuti, quindi\u00a0unite i calamari  e rosolateli per circa - minuti a fuoco vivace, mescolando spesso . A questo punto togliete l\u2019aglio .\u00a0Versate i pomodorini tagliati , salate e pepate. Aggiungete anche i capperi  e lasciate cuocere per\u00a0altri - minuti.\u00a0Cuocete la pasta, nell'acqua che ormai avr\u00e0 raggiunto il bollore per - minuti . Scolate la pasta, tenendo da parte l'acqua di cottura, e trasferitela nel condimento . Aggiungete un mestolo di acqua di cottura e mescolate bene.\u00a0In ultimo aggiungete\u00a0il prezzemolo tritato  e un filo di olio. Saltate le tagliatelle  e servitele ben calde !\u00a0", "ingredients": [["Farina 00", "300 g"], ["Uova", "3"], ["Calamari", "gi\u00e0 puliti 500 g"], ["Pomodorini ciliegino", "400 g"], ["Aglio", "1 spicchio"], ["Olio extravergine d'oliva", "q.b."], ["Capperi sott'olio", "10 g"], ["Sale fino", "q.b."], ["Pepe nero", "q.b."], ["Prezzemolo", "q.b."]], "contesto": "Il risultato finale sar\u00e0 un piatto di tagliatelle fatte in casa, condite con calamari teneri e pomodorini ciliegino freschi, arricchito da capperi, aglio, olio extravergine d'oliva e prezzemolo. Il piatto sar\u00e0 saporito e particolarmente gustoso grazie alla combinazione di sapori dei calamari e dei pomodorini.\n\nQuesto piatto \u00e8 adatto per occasioni speciali come cene in famiglia o per sorprendere gli amici con una ricetta gourmet. \u00c8 perfetto anche per un pranzo leggero o una cena romantica.\n\nLe tagliatelle con calamari e pomodorini sono adatte a una dieta mediterranea e possono essere consumate anche in una dieta equilibrata e sana. Non sono adatte per diete specifiche come la dieta vegetariana o vegana.\n\nLe persone con intolleranze al glutine non possono consumare questo piatto a meno che non usino farina senza glutine per preparare le tagliatelle. Le persone con intolleranze ai frutti di mare devono evitare di consumare questo piatto a causa dei calamari."}