{"title": "Tomino al forno", "category": "Secondi piatti", "description": "Per realizzare i tomini al forno, iniziate a preparare gli ingredienti che vi serviranno per la ricetta: tagliate a met\u00e0 i fichi secchi , tritate grossolanamente i gherigli di noci , infine separate gli aghi di rosmarino dai rametti .Mettete i fichi in una ciotola, aggiungete le noci  e il rosmarino , poi condite con un filo di olio d'oliva ,sale  e pepe. Mescolate bene il composto e versatelo in una teglia abbastanza grande da contenere tutti e  i tomini , distribuitelo uniformemente sul fondo e condite con un altro filo d'olio .Versate l'olio e il pangrattato in due ciotole separate: immergete solo un lato del tomino nell'olio , poi passate lo stesso lato nel pangrattato . Adagiate i tomini nella teglia con il lato impanato rivolto verso l'alto ,aggiungete ancora una macinata di pepe  e cuocete in forno statico preriscaldato a \u00b0 per  minuti. Trascorso questo tempo, passate alla modalit\u00e0 grill e cuocete per altri  minuti. Sfornate i vostri tomini al forno  e serviteli ben caldi per assicurarvi l'effetto filante !", "ingredients": [["Tomini", "(4 pezzi) 370 g"], ["Fichi secchi", "100 g"], ["Noci", "60 g"], ["Rosmarino", "2 rametti"], ["Olio extravergine d'oliva", "q.b."], ["Sale fino", "q.b."], ["Pepe nero", "q.b."], ["Pangrattato", "70 g"], ["Olio extravergine d'oliva", "40 g"]], "contesto": "Il risultato finale della ricetta Tomino al forno sar\u00e0 un piatto ricco e saporito, con i tomini morbidi e cremosi all'interno e una crosta croccante e aromatica. I fichi secchi aggiungono un tocco dolce, le noci conferiscono croccantezza e il rosmarino dona profumo e sapore.\n\nQuesto piatto \u00e8 adatto per un pranzo o una cena in famiglia o con gli amici, pu\u00f2 essere servito come secondo piatto principale o come antipasto. Si abbina bene con contorni di verdure fresche o insalate miste.\n\nLa ricetta del Tomino al forno \u00e8 adatta a persone che seguono una dieta equilibrata, senza particolari restrizioni, in quanto contiene proteine, grassi e carboidrati in quantit\u00e0 bilanciata. Tuttavia, va consumato con moderazione a causa del contenuto calorico elevato.\n\nLe persone con intolleranze alimentari al lattosio dovrebbero evitare questo piatto, poich\u00e9 i tomini contengono latte. Inoltre, chi \u00e8 allergico alle noci o sensibile al glutine dovrebbe fare attenzione all'uso di pangrattato nell'impasto. \u00c8 consigliabile consultare un medico o un nutrizionista prima di consumare questo piatto se si hanno intolleranze alimentari specifiche."}