{
    "title": "Gnocchi di zucchine",
    "category": "Ricette",
    "description": "Per preparare gli gnocchi di zucchine iniziate a mettere a bollire le patate per circa 50 minuti o fino a quando non risulteranno morbide. Testate la cottura con i rebbi della forchetta per regolarvi al meglio. Nel frattempo lavate le zucchine, spuntatele e tagliate a rondelle, ne otterrete così circa 515 g. In una padella versate l’olio e l’aglio, lasciate insaporire qualche istante, poi versate le zucchine. Salate, pepate, aromatizzate con le foglioline di timoe cuocete le zucchine per circa 10 minuti a fuoco medio, o finché non risulteranno cotte. Il tempo varia in base alla grandezza delle zucchine. Eliminate l'aglio, versate le zucchine in un bicchiere dal bordo altoe frullate con il mixer a immersione, per creare una pureaquindi passatela al setaccioe tenetela da parte a raffreddare. Ora versate la farina sulla spianatoia, aggiungete le patate cotte, ormai fredde, passate nello schiacciapatate. Unite la purea di zucchine, la paprikae il formaggio grattugiato. Per ultimo incorporate l’uovo intero. Impastate energicamentefino a ottenere un panetto omogeneo. L’impasto risulterà molto delicato e morbido, prendete un pezzetto di impasto e formate dei filoncini. Tagliate i filoncini a tocchetti di circa 2 cme passate delicatamente gli gnocchi sull’apposito attrezzo riga gnocchi. Ricoprite un vassoio con un canovaccio pulito e spolverizzato con la farina, adagiate qui gli gnocchi rigati ben distanziati. Proseguite cosi fino a terminare l'impasto e poi procedete con la cottura accompagnando gli gnocchi di zucchine con i condimenti che più gradite!",
    "ingredients": [
        [
            "Patate",
            "550 g"
        ],
        [
            "Sale fino",
            "q.b."
        ],
        [
            "Paprika dolce",
            "1 cucchiaino"
        ],
        [
            "Uova",
            "( 1 medio) 57 g"
        ],
        [
            "Grana Padano DOP",
            "60 g"
        ],
        [
            "Farina 00",
            "320 g"
        ],
        [
            "Zucchine",
            "da pulire 550 g"
        ],
        [
            "Aglio",
            "1 spicchio"
        ],
        [
            "Timo",
            "5 rametti"
        ],
        [
            "Olio extravergine d'oliva",
            "q.b."
        ],
        [
            "Pepe nero",
            "q.b."
        ],
        [
            "Sale fino",
            "q.b."
        ]
    ],
    "details": {
        "Difficoltà": "Media",
        "Preparazione": "40 min",
        "Cottura": "50 min",
        "Dosi per": "4 persone",
        "Costo": "Basso"
    }
}