{
    "title": "Risotto zafferano e funghi",
    "category": "Ricette",
    "description": "Per preparare il risotto zafferano e funghi per prima cosa mettete i porcini secchi in ammollo in acqua fredda per circa 15 minuti. Trascorso questo tempo prelevate i funghie tagliateli grossolanamente. Filtrate l’acqua di ammollo attraverso un setaccio foderato con carta assorbentee tenete il liquido da parte. Nel frattempo portate a bollore una pentola di acqua salata che vi servirà per portare il riso a cottura. Mondate e tritate finemente lo scalogno. Fate stufare lo scalogno in una casseruola con un filo d’olio, a fiamma bassa. Quando sarà morbido e trasparente unite il risoe tostatelo per qualche minuto mescolando spesso. A questo punto alzate leggermente la fiamma e sfumate con il vino bianco; lasciate evaporare completamente la parte alcolica, poi versate l’acqua di ammollo dei funghi. Mescolate e iniziate a cuocere il riso aggiungendo un mestolo di acqua calda salata per volta, avendo cura di aspettare sempre che il liquido sia stato assorbito prima di versare il successivo. Quando il riso sarà a metà cottura unite i funghie mescolate, continuando a cuocere il riso. 5 minuti prima della fine della cottura versate lo zafferano in una ciotolina a parte con un paio di cucchiai di acqua calda. Mescolate per scioglierlo, poi unitelo al risoe amalgamate bene. A fine cottura spegnete il fuoco e mantecate con il burro freddoe il Parmigiano Reggiano DOP grattugiato, poi aggiungete una macinata di pepe. Completate con il prezzemolo tritatoe mescolate il tutto. Il vostro risotto zafferano e funghi è pronto per essere servito!",
    "ingredients": [
        [
            "Riso Carnaroli",
            "320 g"
        ],
        [
            "Funghi porcini",
            "secchi 40 g"
        ],
        [
            "Scalogno",
            "1"
        ],
        [
            "Zafferano",
            "(2 bustine da 0,15 g cad) 0,3 g"
        ],
        [
            "Vino bianco",
            "50 g"
        ],
        [
            "Prezzemolo",
            "(da tritare) q.b."
        ],
        [
            "Olio extravergine d'oliva",
            "q.b."
        ],
        [
            "Pepe nero",
            "q.b."
        ],
        [
            "Parmigiano Reggiano DOP",
            "(da grattugiare) 40 g"
        ],
        [
            "Burro",
            "freddo 30 g"
        ]
    ],
    "details": {
        "Difficoltà": "Facile",
        "Preparazione": "10 min",
        "Cottura": "20 min",
        "Dosi per": "4 persone"
    }
}