{
    "title": "Torta con cioccolato al latte",
    "category": "Ricette",
    "description": "Per preparare la torta al cioccolato al latte come prima cosa tritate finemente il cioccolato. Trasferitelo in una bastardellae scioglietelo a bagnomaria. In alternativa potete fondere il cioccolato in microonde, azionandolo pochi secondi alla volta e girandolo spesso. Trasferite in una ciotola il burro morbido, aggiungete lo zuccheroe un pizzico di sale. Lavorate con le fruste elettriche sino ad ottenere un composto leggermente montato. Aggiungete le uova una alla voltaaspettando che la prima sia ben assorbita prima di aggiungere la successiva. Lavorate sino a che non saranno ben assorbite. Versate ora il cioccolato fuso intiepiditoe incorporatelo con le fruste elettriche a velocità bassa. Aggiungete anche la farina 00. Versate anche il lievito, preferibilmente setacciandoloe mescolate ancora, sempre a velocità bassa. Lavorate il tempo strettamente necessario ad ottenere un composto omogeneo. Versate l'impasto ottenuto in uno stampo a cerniera da 22 cm, rivestito con carta forno; in alternativa è possibile imburrarlo e infarinarlo. Livellate la superficie con il dorso di un cucchiaioe cuocete in forno statico preriscaldato a 180° per 40 minuti. Fate sempre la prova dello stecchino prima di sfornare il dolce. Lasciate raffreddare la torta prima di estrarla dallo stampo, trasferitela su un piatto da portata, spolverizzatela con cacao amaroe zucchero a velo e servitela.",
    "ingredients": [
        [
            "Cioccolato al latte",
            "225 g"
        ],
        [
            "Uova",
            "(circa 5 piccole) 220 g"
        ],
        [
            "Burro",
            "a temperatura ambiente 180 g"
        ],
        [
            "Zucchero",
            "100 g"
        ],
        [
            "Farina 00",
            "150 g"
        ],
        [
            "Lievito in polvere per dolci",
            "8 g"
        ],
        [
            "Sale fino",
            "1 pizzico"
        ],
        [
            "Zucchero a velo",
            "q.b."
        ],
        [
            "Cacao amaro in polvere",
            "q.b."
        ]
    ],
    "details": {
        "Difficoltà": "Facile",
        "Preparazione": "20 min",
        "Cottura": "40 min",
        "Dosi per": "6 persone",
        "Costo": "Basso"
    }
}